{"language": "ja", "textAngle": 0.0, "orientation": "Up", "regions": [{"boundingBox": "341,300,1385,910", "lines": [{"boundingBox": "848,300,27,896", "words": [{"boundingBox": "852,300,14,20", "text": "ら"}, {"boundingBox": "848,321,20,25", "text": "往"}, {"boundingBox": "848,352,20,19", "text": "宅"}, {"boundingBox": "850,380,17,15", "text": "の"}, {"boundingBox": "849,405,20,18", "text": "優"}, {"boundingBox": "849,428,21,18", "text": "劣"}, {"boundingBox": "849,454,19,19", "text": "適"}, {"boundingBox": "849,480,20,19", "text": "否"}, {"boundingBox": "851,506,19,16", "text": "り"}, {"boundingBox": "850,531,20,19", "text": "影"}, {"boundingBox": "849,555,21,20", "text": "響"}, {"boundingBox": "853,581,15,18", "text": "を"}, {"boundingBox": "850,607,20,20", "text": "痛"}, {"boundingBox": "849,634,22,19", "text": "切"}, {"boundingBox": "851,660,17,16", "text": "に"}, {"boundingBox": "851,685,20,19", "text": "成"}, {"boundingBox": "850,711,22,19", "text": "ず"}, {"boundingBox": "854,737,14,16", "text": "る"}, {"boundingBox": "853,763,19,15", "text": "り"}, {"boundingBox": "853,788,18,16", "text": "は"}, {"boundingBox": "851,814,21,19", "text": "婦"}, {"boundingBox": "852,838,20,18", "text": "人"}, {"boundingBox": "852,865,21,18", "text": "て"}, {"boundingBox": "853,890,19,19", "text": "あ"}, {"boundingBox": "855,917,15,17", "text": "る"}, {"boundingBox": "866,936,7,5", "text": "。"}, {"boundingBox": "853,942,21,20", "text": "臺"}, {"boundingBox": "853,969,21,19", "text": "所"}, {"boundingBox": "854,995,19,16", "text": "の"}, {"boundingBox": "853,1020,22,19", "text": "構"}, {"boundingBox": "853,1045,21,19", "text": "造"}, {"boundingBox": "853,1067,21,24", "text": "保"}, {"boundingBox": "853,1098,22,19", "text": "光"}, {"boundingBox": "855,1126,19,15", "text": "の"}, {"boundingBox": "854,1149,20,19", "text": "調"}, {"boundingBox": "854,1175,20,21", "text": "節"}]}, {"boundingBox": "936,300,18,52", "words": [{"boundingBox": "936,300,15,21", "text": "ら"}, {"boundingBox": "936,327,14,18", "text": "う"}, {"boundingBox": "948,347,6,5", "text": "・"}]}, {"boundingBox": "761,301,29,901", "words": [{"boundingBox": "761,301,23,20", "text": "俟"}, {"boundingBox": "765,329,18,17", "text": "た"}, {"boundingBox": "762,353,22,20", "text": "ず"}, {"boundingBox": "778,373,5,5", "text": "、"}, {"boundingBox": "763,380,20,18", "text": "時"}, {"boundingBox": "764,405,18,16", "text": "に"}, {"boundingBox": "764,430,19,17", "text": "は"}, {"boundingBox": "766,455,16,19", "text": "自"}, {"boundingBox": "767,480,15,21", "text": "ら"}, {"boundingBox": "764,506,19,20", "text": "意"}, {"boundingBox": "764,531,20,19", "text": "見"}, {"boundingBox": "767,557,16,18", "text": "を"}, {"boundingBox": "769,583,13,19", "text": "も"}, {"boundingBox": "766,609,20,18", "text": "吐"}, {"boundingBox": "768,635,17,24", "text": "ミ"}, {"boundingBox": "766,661,20,19", "text": "時"}, {"boundingBox": "767,688,17,16", "text": "に"}, {"boundingBox": "767,713,18,17", "text": "は"}, {"boundingBox": "768,739,18,17", "text": "見"}, {"boundingBox": "766,763,20,19", "text": "格"}, {"boundingBox": "766,790,20,18", "text": "好"}, {"boundingBox": "767,814,20,20", "text": "等"}, {"boundingBox": "766,841,21,19", "text": "鉛"}, {"boundingBox": "767,867,21,19", "text": "筆"}, {"boundingBox": "771,892,15,18", "text": "を"}, {"boundingBox": "768,918,20,18", "text": "手"}, {"boundingBox": "769,944,17,16", "text": "に"}, {"boundingBox": "773,971,15,17", "text": "し"}, {"boundingBox": "770,996,16,16", "text": "て"}, {"boundingBox": "769,1020,18,18", "text": "示"}, {"boundingBox": "770,1047,17,19", "text": "す"}, {"boundingBox": "773,1073,13,19", "text": "も"}, {"boundingBox": "769,1099,21,19", "text": "立"}, {"boundingBox": "770,1125,20,18", "text": "か"}, {"boundingBox": "775,1150,13,19", "text": "ら"}, {"boundingBox": "774,1176,12,18", "text": "う"}, {"boundingBox": "783,1195,7,7", "text": "・"}]}, {"boundingBox": "805,301,27,893", "words": [{"boundingBox": "806,301,19,21", "text": "隣"}, {"boundingBox": "806,327,20,19", "text": "家"}, {"boundingBox": "808,353,14,19", "text": "と"}, {"boundingBox": "807,381,18,15", "text": "の"}, {"boundingBox": "807,404,18,19", "text": "關"}, {"boundingBox": "805,430,21,19", "text": "係"}, {"boundingBox": "806,480,20,20", "text": "等"}, {"boundingBox": "808,506,18,17", "text": "は"}, {"boundingBox": "807,531,21,19", "text": "主"}, {"boundingBox": "807,557,20,19", "text": "婦"}, {"boundingBox": "808,584,18,16", "text": "の"}, {"boundingBox": "807,609,21,19", "text": "研"}, {"boundingBox": "808,634,19,20", "text": "究"}, {"boundingBox": "809,662,18,15", "text": "の"}, {"boundingBox": "808,686,20,18", "text": "好"}, {"boundingBox": "809,712,20,20", "text": "資"}, {"boundingBox": "809,738,21,18", "text": "粁"}, {"boundingBox": "808,763,21,18", "text": "ゼ"}, {"boundingBox": "810,789,19,18", "text": "あ"}, {"boundingBox": "810,818,18,14", "text": "っ"}, {"boundingBox": "811,840,16,16", "text": "て"}, {"boundingBox": "824,858,5,5", "text": "、"}, {"boundingBox": "810,865,21,19", "text": "大"}, {"boundingBox": "810,892,21,17", "text": "工"}, {"boundingBox": "811,919,19,15", "text": "の"}, {"boundingBox": "811,944,20,18", "text": "手"}, {"boundingBox": "812,968,17,16", "text": "に"}, {"boundingBox": "811,995,20,19", "text": "依"}, {"boundingBox": "816,1019,14,21", "text": "ら"}, {"boundingBox": "810,1045,22,25", "text": "ず"}, {"boundingBox": "811,1073,21,17", "text": "父"}, {"boundingBox": "811,1097,21,20", "text": "専"}, {"boundingBox": "813,1124,18,18", "text": "円"}, {"boundingBox": "812,1148,20,19", "text": "家"}, {"boundingBox": "816,1175,16,19", "text": "ヒ"}]}, {"boundingBox": "720,302,26,895", "words": [{"boundingBox": "721,302,19,20", "text": "斯"}, {"boundingBox": "725,329,9,18", "text": "く"}, {"boundingBox": "722,354,17,20", "text": "す"}, {"boundingBox": "721,379,19,18", "text": "れ"}, {"boundingBox": "720,405,22,19", "text": "ば"}, {"boundingBox": "721,431,18,18", "text": "棚"}, {"boundingBox": "721,457,18,14", "text": "の"}, {"boundingBox": "722,481,19,18", "text": "取"}, {"boundingBox": "722,507,19,18", "text": "附"}, {"boundingBox": "722,532,19,18", "text": "具"}, {"boundingBox": "723,557,18,19", "text": "合"}, {"boundingBox": "722,583,19,18", "text": "か"}, {"boundingBox": "727,609,13,19", "text": "ら"}, {"boundingBox": "737,629,5,5", "text": "、"}, {"boundingBox": "723,635,19,20", "text": "臺"}, {"boundingBox": "723,661,19,19", "text": "所"}, {"boundingBox": "724,688,18,16", "text": "の"}, {"boundingBox": "723,712,20,19", "text": "位"}, {"boundingBox": "724,739,20,19", "text": "置"}, {"boundingBox": "724,764,20,20", "text": "等"}, {"boundingBox": "725,790,17,17", "text": "は"}, {"boundingBox": "725,816,19,19", "text": "男"}, {"boundingBox": "724,842,20,18", "text": "子"}, {"boundingBox": "729,867,12,18", "text": "も"}, {"boundingBox": "725,893,19,18", "text": "及"}, {"boundingBox": "725,919,20,19", "text": "ば"}, {"boundingBox": "726,945,16,19", "text": "な"}, {"boundingBox": "725,974,18,14", "text": "い"}, {"boundingBox": "725,996,18,19", "text": "名"}, {"boundingBox": "725,1021,19,20", "text": "案"}, {"boundingBox": "726,1047,20,21", "text": "が"}, {"boundingBox": "725,1073,20,19", "text": "浮"}, {"boundingBox": "726,1100,20,20", "text": "ば"}, {"boundingBox": "728,1125,16,19", "text": "な"}, {"boundingBox": "727,1155,17,13", "text": "い"}, {"boundingBox": "730,1177,14,20", "text": "と"}]}, {"boundingBox": "590,303,30,894", "words": [{"boundingBox": "590,303,23,19", "text": "味"}, {"boundingBox": "591,332,21,16", "text": "の"}, {"boundingBox": "592,356,19,19", "text": "な"}, {"boundingBox": "590,385,22,12", "text": "い"}, {"boundingBox": "591,406,22,19", "text": "事"}, {"boundingBox": "590,430,24,18", "text": "ゼ"}, {"boundingBox": "594,457,16,17", "text": "も"}, {"boundingBox": "609,475,5,5", "text": "、"}, {"boundingBox": "590,482,24,20", "text": "努"}, {"boundingBox": "592,510,22,15", "text": "め"}, {"boundingBox": "593,534,20,16", "text": "て"}, {"boundingBox": "591,558,24,20", "text": "共"}, {"boundingBox": "593,585,21,16", "text": "の"}, {"boundingBox": "593,611,23,19", "text": "改"}, {"boundingBox": "593,636,23,19", "text": "善"}, {"boundingBox": "593,662,23,19", "text": "研"}, {"boundingBox": "595,688,21,18", "text": "究"}, {"boundingBox": "597,714,19,18", "text": "を"}, {"boundingBox": "595,739,22,19", "text": "怠"}, {"boundingBox": "600,766,15,18", "text": "ら"}, {"boundingBox": "597,791,19,18", "text": "な"}, {"boundingBox": "595,817,22,17", "text": "か"}, {"boundingBox": "596,844,20,14", "text": "っ"}, {"boundingBox": "595,868,21,17", "text": "力"}, {"boundingBox": "597,893,19,19", "text": "な"}, {"boundingBox": "601,919,15,18", "text": "ら"}, {"boundingBox": "595,945,24,19", "text": "ば"}, {"boundingBox": "612,965,6,5", "text": "、"}, {"boundingBox": "595,971,23,17", "text": "次"}, {"boundingBox": "596,997,22,19", "text": "第"}, {"boundingBox": "598,1024,18,15", "text": "に"}, {"boundingBox": "597,1048,22,19", "text": "興"}, {"boundingBox": "597,1074,23,20", "text": "が"}, {"boundingBox": "597,1100,22,18", "text": "桑"}, {"boundingBox": "599,1128,19,14", "text": "っ"}, {"boundingBox": "601,1152,17,16", "text": "て"}, {"boundingBox": "602,1177,15,20", "text": "自"}]}, {"boundingBox": "677,303,27,894", "words": [{"boundingBox": "680,303,13,19", "text": "も"}, {"boundingBox": "677,328,19,20", "text": "限"}, {"boundingBox": "681,354,12,20", "text": "ら"}, {"boundingBox": "679,381,16,18", "text": "な"}, {"boundingBox": "678,411,18,11", "text": "い"}, {"boundingBox": "689,425,9,5", "text": "・"}, {"boundingBox": "681,431,14,17", "text": "を"}, {"boundingBox": "679,456,18,17", "text": "れ"}, {"boundingBox": "680,481,15,15", "text": "に"}, {"boundingBox": "683,507,15,18", "text": "し"}, {"boundingBox": "681,533,15,16", "text": "て"}, {"boundingBox": "683,559,12,17", "text": "も"}, {"boundingBox": "679,583,20,19", "text": "飛"}, {"boundingBox": "679,609,20,19", "text": "が"}, {"boundingBox": "681,664,18,16", "text": "の"}, {"boundingBox": "680,688,20,18", "text": "婦"}, {"boundingBox": "680,713,20,18", "text": "人"}, {"boundingBox": "682,740,18,16", "text": "の"}, {"boundingBox": "680,764,21,19", "text": "建"}, {"boundingBox": "681,790,21,19", "text": "梟"}, {"boundingBox": "683,817,17,16", "text": "に"}, {"boundingBox": "681,842,20,19", "text": "對"}, {"boundingBox": "683,867,17,19", "text": "す"}, {"boundingBox": "685,894,14,16", "text": "る"}, {"boundingBox": "682,919,20,18", "text": "題"}, {"boundingBox": "683,944,19,19", "text": "味"}, {"boundingBox": "681,970,22,20", "text": "が"}, {"boundingBox": "683,996,17,20", "text": "ま"}, {"boundingBox": "683,1021,19,21", "text": "だ"}, {"boundingBox": "688,1053,11,18", "text": "え"}, {"boundingBox": "689,1072,7,20", "text": "\\"}, {"boundingBox": "683,1100,21,18", "text": "不"}, {"boundingBox": "683,1126,21,18", "text": "足"}, {"boundingBox": "683,1150,21,20", "text": "て"}, {"boundingBox": "685,1177,19,20", "text": "あ"}]}, {"boundingBox": "549,304,27,891", "words": [{"boundingBox": "549,304,21,20", "text": "然"}, {"boundingBox": "550,330,21,20", "text": "共"}, {"boundingBox": "552,358,17,15", "text": "の"}, {"boundingBox": "551,381,19,19", "text": "智"}, {"boundingBox": "551,406,20,20", "text": "識"}, {"boundingBox": "554,432,15,18", "text": "を"}, {"boundingBox": "551,458,20,18", "text": "増"}, {"boundingBox": "552,483,18,19", "text": "す"}, {"boundingBox": "557,510,11,18", "text": "も"}, {"boundingBox": "553,536,18,15", "text": "の"}, {"boundingBox": "551,559,20,19", "text": "ゼ"}, {"boundingBox": "554,585,17,20", "text": "あ"}, {"boundingBox": "556,613,14,17", "text": "る"}, {"boundingBox": "566,631,5,5", "text": "。"}, {"boundingBox": "552,638,20,18", "text": "從"}, {"boundingBox": "554,666,17,13", "text": "っ"}, {"boundingBox": "555,689,16,17", "text": "て"}, {"boundingBox": "554,714,20,20", "text": "他"}, {"boundingBox": "555,743,18,17", "text": "人"}, {"boundingBox": "555,768,18,15", "text": "の"}, {"boundingBox": "555,792,19,18", "text": "建"}, {"boundingBox": "555,817,19,20", "text": "築"}, {"boundingBox": "557,843,15,18", "text": "を"}, {"boundingBox": "555,869,20,18", "text": "眦"}, {"boundingBox": "555,895,19,18", "text": "評"}, {"boundingBox": "557,919,17,19", "text": "す"}, {"boundingBox": "559,946,13,17", "text": "る"}, {"boundingBox": "559,973,13,16", "text": "こ"}, {"boundingBox": "559,997,13,19", "text": "と"}, {"boundingBox": "560,1023,12,18", "text": "も"}, {"boundingBox": "571,1042,4,5", "text": "・"}, {"boundingBox": "557,1048,17,20", "text": "新"}, {"boundingBox": "558,1077,16,15", "text": "に"}, {"boundingBox": "559,1101,17,18", "text": "設"}, {"boundingBox": "557,1126,19,20", "text": "計"}, {"boundingBox": "560,1153,13,17", "text": "さ"}, {"boundingBox": "559,1177,17,18", "text": "れ"}]}, {"boundingBox": "632,304,32,892", "words": [{"boundingBox": "635,304,16,18", "text": "る"}, {"boundingBox": "636,329,16,20", "text": "と"}, {"boundingBox": "632,356,23,18", "text": "思"}, {"boundingBox": "634,382,22,23", "text": "ら"}, {"boundingBox": "633,406,23,19", "text": "要"}, {"boundingBox": "634,432,20,17", "text": "す"}, {"boundingBox": "637,457,16,16", "text": "る"}, {"boundingBox": "635,483,19,16", "text": "に"}, {"boundingBox": "634,508,24,18", "text": "建"}, {"boundingBox": "635,533,23,19", "text": "築"}, {"boundingBox": "635,559,23,18", "text": "趣"}, {"boundingBox": "635,584,23,18", "text": "味"}, {"boundingBox": "637,612,20,15", "text": "の"}, {"boundingBox": "635,635,24,20", "text": "普"}, {"boundingBox": "635,662,23,18", "text": "及"}, {"boundingBox": "637,688,21,16", "text": "は"}, {"boundingBox": "653,706,6,4", "text": "、"}, {"boundingBox": "635,713,25,20", "text": "婦"}, {"boundingBox": "638,741,22,17", "text": "人"}, {"boundingBox": "639,765,19,16", "text": "に"}, {"boundingBox": "637,791,24,18", "text": "取"}, {"boundingBox": "643,817,12,17", "text": "り"}, {"boundingBox": "640,843,18,16", "text": "て"}, {"boundingBox": "639,869,21,17", "text": "は"}, {"boundingBox": "640,894,20,17", "text": "刻"}, {"boundingBox": "638,919,23,18", "text": "下"}, {"boundingBox": "639,947,22,15", "text": "の"}, {"boundingBox": "637,971,25,20", "text": "急"}, {"boundingBox": "638,997,24,19", "text": "務"}, {"boundingBox": "655,1022,8,4", "text": "・"}, {"boundingBox": "639,1027,21,14", "text": "て"}, {"boundingBox": "641,1048,21,19", "text": "あ"}, {"boundingBox": "641,1077,20,14", "text": "っ"}, {"boundingBox": "641,1100,19,16", "text": "て"}, {"boundingBox": "656,1119,6,5", "text": "、"}, {"boundingBox": "639,1126,25,19", "text": "継"}, {"boundingBox": "640,1152,24,19", "text": "令"}, {"boundingBox": "641,1178,23,18", "text": "興"}]}, {"boundingBox": "462,330,32,868", "words": [{"boundingBox": "462,330,24,21", "text": "型"}, {"boundingBox": "469,357,15,18", "text": "を"}, {"boundingBox": "467,382,19,18", "text": "作"}, {"boundingBox": "469,411,17,14", "text": "っ"}, {"boundingBox": "469,434,15,15", "text": "て"}, {"boundingBox": "467,458,20,18", "text": "見"}, {"boundingBox": "469,484,17,16", "text": "た"}, {"boundingBox": "474,509,8,16", "text": "与"}, {"boundingBox": "469,534,17,20", "text": "す"}, {"boundingBox": "471,561,13,15", "text": "る"}, {"boundingBox": "469,585,19,20", "text": "内"}, {"boundingBox": "470,612,17,18", "text": "に"}, {"boundingBox": "482,631,6,4", "text": "、"}, {"boundingBox": "467,638,21,20", "text": "知"}, {"boundingBox": "474,663,13,20", "text": "ら"}, {"boundingBox": "469,689,22,19", "text": "ず"}, {"boundingBox": "469,715,21,20", "text": "識"}, {"boundingBox": "474,740,14,18", "text": "ら"}, {"boundingBox": "469,766,22,19", "text": "ず"}, {"boundingBox": "470,792,21,18", "text": "建"}, {"boundingBox": "470,817,21,20", "text": "築"}, {"boundingBox": "470,844,21,18", "text": "趣"}, {"boundingBox": "471,869,20,17", "text": "味"}, {"boundingBox": "473,895,17,18", "text": "を"}, {"boundingBox": "471,920,20,19", "text": "溷"}, {"boundingBox": "472,972,18,19", "text": "す"}, {"boundingBox": "475,998,14,17", "text": "る"}, {"boundingBox": "475,1025,15,15", "text": "こ"}, {"boundingBox": "476,1049,14,20", "text": "と"}, {"boundingBox": "472,1075,22,19", "text": "が"}, {"boundingBox": "473,1100,19,19", "text": "出"}, {"boundingBox": "472,1126,22,19", "text": "來"}, {"boundingBox": "476,1153,14,16", "text": "る"}, {"boundingBox": "477,1180,13,18", "text": "も"}]}, {"boundingBox": "510,305,26,893", "words": [{"boundingBox": "511,305,17,18", "text": "た"}, {"boundingBox": "515,331,11,18", "text": "も"}, {"boundingBox": "511,358,17,16", "text": "の"}, {"boundingBox": "512,382,16,17", "text": "に"}, {"boundingBox": "510,407,20,19", "text": "對"}, {"boundingBox": "516,434,14,17", "text": "し"}, {"boundingBox": "513,459,15,14", "text": "て"}, {"boundingBox": "514,483,13,18", "text": "も"}, {"boundingBox": "526,503,4,4", "text": "・"}, {"boundingBox": "515,509,13,19", "text": "自"}, {"boundingBox": "513,535,17,18", "text": "己"}, {"boundingBox": "513,561,18,15", "text": "の"}, {"boundingBox": "511,585,20,18", "text": "理"}, {"boundingBox": "513,612,19,19", "text": "想"}, {"boundingBox": "515,637,15,19", "text": "を"}, {"boundingBox": "515,690,15,14", "text": "て"}, {"boundingBox": "513,714,20,19", "text": "嵌"}, {"boundingBox": "515,742,17,17", "text": "め"}, {"boundingBox": "516,768,15,16", "text": "て"}, {"boundingBox": "514,792,19,18", "text": "見"}, {"boundingBox": "517,819,13,16", "text": "る"}, {"boundingBox": "518,845,13,16", "text": "こ"}, {"boundingBox": "518,869,12,19", "text": "と"}, {"boundingBox": "518,895,13,18", "text": "も"}, {"boundingBox": "517,920,16,20", "text": "出"}, {"boundingBox": "515,947,20,18", "text": "來"}, {"boundingBox": "529,966,5,5", "text": "、"}, {"boundingBox": "516,973,18,19", "text": "時"}, {"boundingBox": "518,998,15,16", "text": "に"}, {"boundingBox": "517,1024,17,18", "text": "は"}, {"boundingBox": "519,1050,13,19", "text": "自"}, {"boundingBox": "517,1075,18,19", "text": "か"}, {"boundingBox": "522,1100,12,20", "text": "ら"}, {"boundingBox": "518,1127,17,18", "text": "圓"}, {"boundingBox": "517,1151,19,21", "text": "面"}, {"boundingBox": "519,1179,17,19", "text": "や"}]}, {"boundingBox": "423,307,22,101", "words": [{"boundingBox": "424,307,20,17", "text": "の"}, {"boundingBox": "423,331,22,19", "text": "ぞ"}, {"boundingBox": "426,358,19,19", "text": "あ"}, {"boundingBox": "427,385,15,15", "text": "る"}, {"boundingBox": "437,403,7,5", "text": "・"}]}, {"boundingBox": "1095,307,39,892", "words": [{"boundingBox": "1111,307,21,19", "text": "を"}, {"boundingBox": "1112,334,22,18", "text": "好"}, {"boundingBox": "1111,385,22,18", "text": "か"}, {"boundingBox": "1114,409,13,20", "text": "と"}, {"boundingBox": "1111,435,21,17", "text": "云"}, {"boundingBox": "1110,460,20,18", "text": "ス"}, {"boundingBox": "1111,486,19,19", "text": "問"}, {"boundingBox": "1109,511,22,20", "text": "題"}, {"boundingBox": "1111,537,17,19", "text": "を"}, {"boundingBox": "1107,562,23,19", "text": "提"}, {"boundingBox": "1107,587,21,20", "text": "出"}, {"boundingBox": "1111,614,17,18", "text": "し"}, {"boundingBox": "1107,641,18,15", "text": "て"}, {"boundingBox": "1121,659,5,5", "text": "、"}, {"boundingBox": "1105,665,23,19", "text": "之"}, {"boundingBox": "1109,692,16,18", "text": "を"}, {"boundingBox": "1105,717,22,20", "text": "廣"}, {"boundingBox": "1109,743,10,18", "text": "く"}, {"boundingBox": "1103,768,23,20", "text": "募"}, {"boundingBox": "1103,794,22,19", "text": "集"}, {"boundingBox": "1106,820,18,18", "text": "し"}, {"boundingBox": "1102,846,20,17", "text": "た"}, {"boundingBox": "1101,872,23,19", "text": "が"}, {"boundingBox": "1101,896,21,19", "text": "如"}, {"boundingBox": "1104,922,14,20", "text": "き"}, {"boundingBox": "1099,948,23,18", "text": "之"}, {"boundingBox": "1102,974,17,18", "text": "を"}, {"boundingBox": "1097,1000,23,19", "text": "證"}, {"boundingBox": "1099,1025,19,19", "text": "明"}, {"boundingBox": "1099,1051,19,19", "text": "す"}, {"boundingBox": "1099,1077,17,17", "text": "る"}, {"boundingBox": "1101,1103,14,19", "text": "も"}, {"boundingBox": "1095,1131,22,15", "text": "の"}, {"boundingBox": "1095,1153,22,20", "text": "て"}, {"boundingBox": "1095,1179,20,20", "text": "あ"}]}, {"boundingBox": "1140,307,38,892", "words": [{"boundingBox": "1157,307,21,20", "text": "宅"}, {"boundingBox": "1157,336,19,16", "text": "の"}, {"boundingBox": "1157,360,19,19", "text": "間"}, {"boundingBox": "1156,385,20,18", "text": "取"}, {"boundingBox": "1155,411,21,18", "text": "不"}, {"boundingBox": "1154,436,21,18", "text": "面"}, {"boundingBox": "1156,461,19,19", "text": "圖"}, {"boundingBox": "1157,486,16,18", "text": "を"}, {"boundingBox": "1153,511,21,20", "text": "募"}, {"boundingBox": "1153,537,21,20", "text": "集"}, {"boundingBox": "1153,563,21,18", "text": "せ"}, {"boundingBox": "1157,589,17,18", "text": "し"}, {"boundingBox": "1152,615,21,19", "text": "が"}, {"boundingBox": "1152,641,19,19", "text": "如"}, {"boundingBox": "1153,665,14,19", "text": "き"}, {"boundingBox": "1151,693,19,16", "text": "又"}, {"boundingBox": "1151,718,19,19", "text": "嘗"}, {"boundingBox": "1151,745,17,16", "text": "て"}, {"boundingBox": "1150,769,19,19", "text": "或"}, {"boundingBox": "1152,796,14,16", "text": "る"}, {"boundingBox": "1147,820,23,20", "text": "婦"}, {"boundingBox": "1147,846,20,18", "text": "人"}, {"boundingBox": "1146,871,21,20", "text": "雑"}, {"boundingBox": "1145,898,22,19", "text": "誌"}, {"boundingBox": "1147,923,18,18", "text": "に"}, {"boundingBox": "1149,950,13,17", "text": "日"}, {"boundingBox": "1144,975,21,20", "text": "本"}, {"boundingBox": "1144,1001,20,18", "text": "家"}, {"boundingBox": "1143,1026,20,19", "text": "屋"}, {"boundingBox": "1147,1051,13,21", "text": "と"}, {"boundingBox": "1143,1078,20,20", "text": "洋"}, {"boundingBox": "1142,1104,20,19", "text": "館"}, {"boundingBox": "1145,1129,14,20", "text": "と"}, {"boundingBox": "1140,1155,22,19", "text": "何"}, {"boundingBox": "1140,1180,20,19", "text": "れ"}]}, {"boundingBox": "1182,308,37,893", "words": [{"boundingBox": "1203,308,13,20", "text": "と"}, {"boundingBox": "1201,339,17,13", "text": "い"}, {"boundingBox": "1200,361,18,17", "text": "ム"}, {"boundingBox": "1198,386,21,19", "text": "雑"}, {"boundingBox": "1198,412,20,18", "text": "誌"}, {"boundingBox": "1198,437,20,18", "text": "社"}, {"boundingBox": "1199,462,18,16", "text": "の"}, {"boundingBox": "1197,487,20,19", "text": "主"}, {"boundingBox": "1197,514,18,18", "text": "唱"}, {"boundingBox": "1198,540,16,16", "text": "に"}, {"boundingBox": "1200,565,11,17", "text": "よ"}, {"boundingBox": "1196,592,18,14", "text": "っ"}, {"boundingBox": "1196,616,16,16", "text": "て"}, {"boundingBox": "1194,641,20,19", "text": "最"}, {"boundingBox": "1193,667,20,18", "text": "近"}, {"boundingBox": "1193,718,19,18", "text": "が"}, {"boundingBox": "1193,745,18,18", "text": "国"}, {"boundingBox": "1192,769,20,19", "text": "ゼ"}, {"boundingBox": "1191,795,20,18", "text": "大"}, {"boundingBox": "1191,821,20,19", "text": "阪"}, {"boundingBox": "1189,846,21,20", "text": "婦"}, {"boundingBox": "1189,872,19,19", "text": "人"}, {"boundingBox": "1189,898,20,19", "text": "博"}, {"boundingBox": "1187,924,21,20", "text": "覧"}, {"boundingBox": "1187,949,20,20", "text": "會"}, {"boundingBox": "1188,977,19,15", "text": "の"}, {"boundingBox": "1187,1001,18,19", "text": "開"}, {"boundingBox": "1187,1027,21,19", "text": "催"}, {"boundingBox": "1188,1053,14,18", "text": "さ"}, {"boundingBox": "1187,1078,15,18", "text": "れ"}, {"boundingBox": "1185,1105,18,18", "text": "カ"}, {"boundingBox": "1184,1131,20,18", "text": "時"}, {"boundingBox": "1185,1156,17,17", "text": "に"}, {"boundingBox": "1182,1181,21,20", "text": "住"}]}, {"boundingBox": "1315,311,32,589", "words": [{"boundingBox": "1327,311,19,19", "text": "爾"}, {"boundingBox": "1326,345,21,5", "text": "一"}, {"boundingBox": "1326,363,21,20", "text": "層"}, {"boundingBox": "1325,389,19,18", "text": "此"}, {"boundingBox": "1326,416,18,15", "text": "の"}, {"boundingBox": "1325,439,18,19", "text": "間"}, {"boundingBox": "1323,465,21,19", "text": "題"}, {"boundingBox": "1325,490,16,17", "text": "に"}, {"boundingBox": "1323,541,17,18", "text": "け"}, {"boundingBox": "1324,567,14,15", "text": "る"}, {"boundingBox": "1319,592,23,19", "text": "研"}, {"boundingBox": "1319,617,21,20", "text": "究"}, {"boundingBox": "1319,643,20,21", "text": "實"}, {"boundingBox": "1318,670,21,18", "text": "行"}, {"boundingBox": "1320,695,16,19", "text": "を"}, {"boundingBox": "1317,720,20,19", "text": "望"}, {"boundingBox": "1317,748,19,16", "text": "む"}, {"boundingBox": "1320,774,13,17", "text": "も"}, {"boundingBox": "1317,799,19,16", "text": "の"}, {"boundingBox": "1315,823,21,19", "text": "ぞ"}, {"boundingBox": "1316,849,18,19", "text": "あ"}, {"boundingBox": "1317,876,17,24", "text": "ゑ"}]}, {"boundingBox": "1350,312,38,894", "words": [{"boundingBox": "1370,312,17,17", "text": "に"}, {"boundingBox": "1368,337,20,20", "text": "開"}, {"boundingBox": "1369,363,18,18", "text": "す"}, {"boundingBox": "1370,389,14,16", "text": "る"}, {"boundingBox": "1366,414,21,19", "text": "議"}, {"boundingBox": "1365,439,22,17", "text": "論"}, {"boundingBox": "1365,464,20,17", "text": "が"}, {"boundingBox": "1365,489,20,19", "text": "行"}, {"boundingBox": "1365,515,19,16", "text": "は"}, {"boundingBox": "1364,540,20,18", "text": "れ"}, {"boundingBox": "1365,567,16,15", "text": "て"}, {"boundingBox": "1377,585,5,4", "text": "・"}, {"boundingBox": "1361,591,23,19", "text": "世"}, {"boundingBox": "1362,618,19,18", "text": "人"}, {"boundingBox": "1365,643,13,19", "text": "も"}, {"boundingBox": "1360,669,22,19", "text": "稍"}, {"boundingBox": "1362,697,16,15", "text": "季"}, {"boundingBox": "1359,720,21,18", "text": "此"}, {"boundingBox": "1360,746,19,18", "text": "れ"}, {"boundingBox": "1359,773,17,15", "text": "に"}, {"boundingBox": "1357,798,22,17", "text": "心"}, {"boundingBox": "1361,823,15,18", "text": "を"}, {"boundingBox": "1357,847,19,19", "text": "向"}, {"boundingBox": "1358,875,18,17", "text": "け"}, {"boundingBox": "1358,900,15,16", "text": "る"}, {"boundingBox": "1354,925,21,20", "text": "様"}, {"boundingBox": "1356,952,17,16", "text": "に"}, {"boundingBox": "1355,977,17,18", "text": "な"}, {"boundingBox": "1354,1005,19,14", "text": "っ"}, {"boundingBox": "1355,1030,17,16", "text": "て"}, {"boundingBox": "1351,1054,22,19", "text": "來"}, {"boundingBox": "1352,1080,19,18", "text": "た"}, {"boundingBox": "1352,1106,20,18", "text": "が"}, {"boundingBox": "1367,1125,4,4", "text": "・"}, {"boundingBox": "1353,1131,15,20", "text": "自"}, {"boundingBox": "1350,1158,20,19", "text": "分"}, {"boundingBox": "1351,1188,17,18", "text": "は"}]}, {"boundingBox": "1452,312,23,179", "words": [{"boundingBox": "1456,312,18,20", "text": "な"}, {"boundingBox": "1454,342,20,13", "text": "い"}, {"boundingBox": "1453,364,22,20", "text": "証"}, {"boundingBox": "1452,389,22,20", "text": "據"}, {"boundingBox": "1452,414,21,19", "text": "ゼ"}, {"boundingBox": "1453,440,18,19", "text": "あ"}, {"boundingBox": "1454,467,16,15", "text": "る"}, {"boundingBox": "1464,485,7,6", "text": "・"}]}, {"boundingBox": "1480,315,38,892", "words": [{"boundingBox": "1502,315,11,18", "text": "歩"}, {"boundingBox": "1497,340,21,18", "text": "ぞ"}, {"boundingBox": "1498,365,18,20", "text": "あ"}, {"boundingBox": "1499,393,15,15", "text": "る"}, {"boundingBox": "1510,411,6,5", "text": "。"}, {"boundingBox": "1495,416,22,18", "text": "之"}, {"boundingBox": "1496,441,20,18", "text": "れ"}, {"boundingBox": "1495,467,21,19", "text": "が"}, {"boundingBox": "1495,492,19,20", "text": "部"}, {"boundingBox": "1497,518,15,19", "text": "ち"}, {"boundingBox": "1492,544,22,18", "text": "世"}, {"boundingBox": "1493,569,19,18", "text": "人"}, {"boundingBox": "1492,595,21,19", "text": "が"}, {"boundingBox": "1490,621,22,19", "text": "建"}, {"boundingBox": "1490,646,22,20", "text": "築"}, {"boundingBox": "1494,672,14,20", "text": "と"}, {"boundingBox": "1491,701,18,13", "text": "い"}, {"boundingBox": "1489,724,19,19", "text": "ふ"}, {"boundingBox": "1488,751,20,19", "text": "事"}, {"boundingBox": "1490,776,17,17", "text": "に"}, {"boundingBox": "1487,801,21,19", "text": "對"}, {"boundingBox": "1491,828,16,17", "text": "し"}, {"boundingBox": "1488,853,16,17", "text": "て"}, {"boundingBox": "1486,878,20,20", "text": "智"}, {"boundingBox": "1485,904,21,20", "text": "識"}, {"boundingBox": "1489,930,13,20", "text": "と"}, {"boundingBox": "1483,957,22,19", "text": "趣"}, {"boundingBox": "1485,982,20,18", "text": "味"}, {"boundingBox": "1487,1008,13,19", "text": "と"}, {"boundingBox": "1482,1033,22,20", "text": "が"}, {"boundingBox": "1481,1059,22,20", "text": "普"}, {"boundingBox": "1481,1086,21,18", "text": "及"}, {"boundingBox": "1483,1113,16,16", "text": "さ"}, {"boundingBox": "1481,1136,18,19", "text": "れ"}, {"boundingBox": "1481,1163,17,17", "text": "て"}, {"boundingBox": "1480,1190,19,17", "text": "ゐ"}]}, {"boundingBox": "1521,315,39,894", "words": [{"boundingBox": "1539,315,21,20", "text": "或"}, {"boundingBox": "1540,341,19,17", "text": "は"}, {"boundingBox": "1537,367,23,19", "text": "建"}, {"boundingBox": "1538,392,21,18", "text": "物"}, {"boundingBox": "1538,419,19,15", "text": "の"}, {"boundingBox": "1537,442,21,18", "text": "大"}, {"boundingBox": "1537,468,20,18", "text": "小"}, {"boundingBox": "1538,494,16,15", "text": "に"}, {"boundingBox": "1539,520,13,17", "text": "よ"}, {"boundingBox": "1536,549,19,13", "text": "っ"}, {"boundingBox": "1537,571,15,15", "text": "て"}, {"boundingBox": "1533,595,21,19", "text": "住"}, {"boundingBox": "1533,623,22,18", "text": "宅"}, {"boundingBox": "1534,649,18,16", "text": "の"}, {"boundingBox": "1531,673,22,19", "text": "優"}, {"boundingBox": "1531,699,21,19", "text": "劣"}, {"boundingBox": "1530,725,22,20", "text": "適"}, {"boundingBox": "1530,752,22,19", "text": "否"}, {"boundingBox": "1533,777,16,18", "text": "を"}, {"boundingBox": "1529,802,21,19", "text": "定"}, {"boundingBox": "1529,829,19,17", "text": "め"}, {"boundingBox": "1531,854,14,16", "text": "る"}, {"boundingBox": "1527,879,21,19", "text": "傾"}, {"boundingBox": "1528,904,18,19", "text": "向"}, {"boundingBox": "1527,931,21,19", "text": "が"}, {"boundingBox": "1527,956,18,20", "text": "あ"}, {"boundingBox": "1529,984,15,17", "text": "る"}, {"boundingBox": "1525,1009,21,18", "text": "が"}, {"boundingBox": "1540,1028,4,5", "text": "・"}, {"boundingBox": "1524,1034,22,18", "text": "之"}, {"boundingBox": "1525,1060,21,18", "text": "れ"}, {"boundingBox": "1525,1085,18,18", "text": "は"}, {"boundingBox": "1523,1111,21,19", "text": "大"}, {"boundingBox": "1525,1138,17,19", "text": "な"}, {"boundingBox": "1525,1165,15,16", "text": "る"}, {"boundingBox": "1521,1189,21,20", "text": "誤"}]}, {"boundingBox": "890,326,28,867", "words": [{"boundingBox": "890,326,20,19", "text": "元"}, {"boundingBox": "890,352,22,18", "text": "來"}, {"boundingBox": "890,378,20,19", "text": "男"}, {"boundingBox": "890,404,21,18", "text": "子"}, {"boundingBox": "892,429,18,17", "text": "は"}, {"boundingBox": "891,453,21,19", "text": "外"}, {"boundingBox": "892,480,18,16", "text": "に"}, {"boundingBox": "893,504,18,20", "text": "あ"}, {"boundingBox": "897,531,10,17", "text": "。"}, {"boundingBox": "893,557,17,16", "text": "て"}, {"boundingBox": "892,581,21,19", "text": "働"}, {"boundingBox": "895,607,13,19", "text": "き"}, {"boundingBox": "907,627,5,4", "text": "、"}, {"boundingBox": "893,635,20,17", "text": "又"}, {"boundingBox": "893,659,20,19", "text": "婦"}, {"boundingBox": "894,685,20,18", "text": "人"}, {"boundingBox": "894,712,19,15", "text": "の"}, {"boundingBox": "894,736,21,18", "text": "大"}, {"boundingBox": "893,762,22,19", "text": "部"}, {"boundingBox": "893,787,22,19", "text": "分"}, {"boundingBox": "895,814,19,16", "text": "は"}, {"boundingBox": "894,838,20,19", "text": "家"}, {"boundingBox": "894,864,21,19", "text": "庭"}, {"boundingBox": "896,890,18,16", "text": "に"}, {"boundingBox": "896,916,19,19", "text": "あ"}, {"boundingBox": "900,944,11,16", "text": "。"}, {"boundingBox": "896,968,17,16", "text": "て"}, {"boundingBox": "895,994,21,19", "text": "働"}, {"boundingBox": "899,1020,11,18", "text": "く"}, {"boundingBox": "899,1046,14,18", "text": "も"}, {"boundingBox": "897,1073,20,16", "text": "の"}, {"boundingBox": "896,1097,22,19", "text": "ぞ"}, {"boundingBox": "898,1123,19,19", "text": "あ"}, {"boundingBox": "900,1149,14,18", "text": "る"}, {"boundingBox": "897,1175,21,18", "text": "か"}]}, {"boundingBox": "379,333,29,864", "words": [{"boundingBox": "379,333,24,17", "text": "理"}, {"boundingBox": "380,359,23,18", "text": "想"}, {"boundingBox": "382,386,20,15", "text": "の"}, {"boundingBox": "381,408,22,18", "text": "住"}, {"boundingBox": "381,433,22,19", "text": "宅"}, {"boundingBox": "385,459,15,19", "text": "と"}, {"boundingBox": "382,485,20,17", "text": "は"}, {"boundingBox": "381,510,21,18", "text": "如"}, {"boundingBox": "382,536,22,18", "text": "何"}, {"boundingBox": "384,562,18,18", "text": "な"}, {"boundingBox": "385,587,17,17", "text": "る"}, {"boundingBox": "381,612,23,19", "text": "住"}, {"boundingBox": "382,639,23,18", "text": "宅"}, {"boundingBox": "397,664,7,3", "text": "-"}, {"boundingBox": "381,668,20,14", "text": "て"}, {"boundingBox": "385,690,20,19", "text": "あ"}, {"boundingBox": "386,717,16,17", "text": "る"}, {"boundingBox": "383,742,23,18", "text": "か"}, {"boundingBox": "399,761,7,5", "text": "、"}, {"boundingBox": "383,768,23,17", "text": "之"}, {"boundingBox": "386,793,18,17", "text": "を"}, {"boundingBox": "384,819,22,18", "text": "略"}, {"boundingBox": "384,845,21,18", "text": "言"}, {"boundingBox": "386,869,20,19", "text": "す"}, {"boundingBox": "384,895,23,17", "text": "れ"}, {"boundingBox": "385,921,22,19", "text": "ば"}, {"boundingBox": "385,946,21,20", "text": "部"}, {"boundingBox": "389,973,19,18", "text": "ち"}, {"boundingBox": "385,992,23,25", "text": "往"}, {"boundingBox": "386,1025,21,19", "text": "み"}, {"boundingBox": "385,1050,22,18", "text": "心"}, {"boundingBox": "386,1076,22,18", "text": "地"}, {"boundingBox": "387,1104,21,15", "text": "の"}, {"boundingBox": "392,1128,13,17", "text": "よ"}, {"boundingBox": "389,1156,19,13", "text": "い"}, {"boundingBox": "388,1179,20,18", "text": "家"}]}, {"boundingBox": "1228,337,34,769", "words": [{"boundingBox": "1241,337,21,19", "text": "住"}, {"boundingBox": "1241,363,21,19", "text": "宅"}, {"boundingBox": "1243,388,15,20", "text": "と"}, {"boundingBox": "1240,414,22,19", "text": "婦"}, {"boundingBox": "1240,439,20,17", "text": "人"}, {"boundingBox": "1242,464,13,18", "text": "と"}, {"boundingBox": "1240,491,19,17", "text": "は"}, {"boundingBox": "1238,516,21,18", "text": "殊"}, {"boundingBox": "1239,541,17,16", "text": "に"}, {"boundingBox": "1238,565,20,19", "text": "密"}, {"boundingBox": "1237,591,21,20", "text": "接"}, {"boundingBox": "1238,617,17,19", "text": "な"}, {"boundingBox": "1236,643,19,20", "text": "關"}, {"boundingBox": "1234,669,21,19", "text": "係"}, {"boundingBox": "1237,694,17,19", "text": "を"}, {"boundingBox": "1234,720,20,19", "text": "有"}, {"boundingBox": "1238,746,16,18", "text": "し"}, {"boundingBox": "1235,773,16,16", "text": "て"}, {"boundingBox": "1235,799,14,16", "text": "る"}, {"boundingBox": "1237,823,12,17", "text": "も"}, {"boundingBox": "1233,850,18,16", "text": "の"}, {"boundingBox": "1232,875,20,17", "text": "("}, {"boundingBox": "1246,894,5,4", "text": "、"}, {"boundingBox": "1231,900,20,19", "text": "米"}, {"boundingBox": "1231,925,18,19", "text": "国"}, {"boundingBox": "1231,953,18,15", "text": "の"}, {"boundingBox": "1239,971,11,7", "text": "「"}, {"boundingBox": "1243,979,5,4", "text": "・"}, {"boundingBox": "1228,983,19,9", "text": "("}, {"boundingBox": "1232,1007,16,11", "text": "ン"}, {"boundingBox": "1229,1028,19,16", "text": "ガ"}, {"boundingBox": "1231,1059,13,9", "text": "0"}, {"boundingBox": "1233,1083,7,13", "text": "ー"}, {"boundingBox": "1241,1100,7,6", "text": "、"}]}, {"boundingBox": "1392,339,40,867", "words": [{"boundingBox": "1410,339,22,18", "text": "型"}, {"boundingBox": "1410,363,22,20", "text": "今"}, {"boundingBox": "1410,388,21,19", "text": "て"}, {"boundingBox": "1410,414,19,17", "text": "は"}, {"boundingBox": "1409,440,21,19", "text": "専"}, {"boundingBox": "1409,465,18,19", "text": "門"}, {"boundingBox": "1406,490,23,19", "text": "家"}, {"boundingBox": "1407,517,21,19", "text": "共"}, {"boundingBox": "1408,544,19,15", "text": "の"}, {"boundingBox": "1405,566,22,20", "text": "他"}, {"boundingBox": "1406,595,19,15", "text": "の"}, {"boundingBox": "1404,618,22,19", "text": "人"}, {"boundingBox": "1403,671,21,19", "text": "が"}, {"boundingBox": "1402,696,22,19", "text": "建"}, {"boundingBox": "1402,722,22,19", "text": "築"}, {"boundingBox": "1401,749,22,18", "text": "趣"}, {"boundingBox": "1401,773,21,19", "text": "味"}, {"boundingBox": "1401,801,19,15", "text": "の"}, {"boundingBox": "1400,825,21,19", "text": "普"}, {"boundingBox": "1400,850,20,18", "text": "及"}, {"boundingBox": "1402,876,16,18", "text": "を"}, {"boundingBox": "1400,902,19,18", "text": "叫"}, {"boundingBox": "1399,928,20,17", "text": "び"}, {"boundingBox": "1411,947,7,6", "text": "。"}, {"boundingBox": "1398,953,20,20", "text": "或"}, {"boundingBox": "1397,980,19,17", "text": "は"}, {"boundingBox": "1395,1004,21,20", "text": "雑"}, {"boundingBox": "1395,1031,21,19", "text": "誌"}, {"boundingBox": "1396,1057,17,17", "text": "に"}, {"boundingBox": "1395,1081,20,19", "text": "新"}, {"boundingBox": "1395,1107,19,19", "text": "聞"}, {"boundingBox": "1395,1137,17,17", "text": "に"}, {"boundingBox": "1393,1160,21,19", "text": "住"}, {"boundingBox": "1392,1187,21,19", "text": "宅"}]}, {"boundingBox": "1564,344,37,866", "words": [{"boundingBox": "1580,344,21,19", "text": "住"}, {"boundingBox": "1579,370,21,20", "text": "宅"}, {"boundingBox": "1582,395,16,19", "text": "を"}, {"boundingBox": "1577,421,23,18", "text": "建"}, {"boundingBox": "1577,445,22,20", "text": "築"}, {"boundingBox": "1578,470,20,20", "text": "す"}, {"boundingBox": "1580,497,15,16", "text": "る"}, {"boundingBox": "1579,522,17,17", "text": "に"}, {"boundingBox": "1577,547,20,19", "text": "當"}, {"boundingBox": "1577,576,19,13", "text": "っ"}, {"boundingBox": "1577,600,17,16", "text": "て"}, {"boundingBox": "1574,624,22,19", "text": "世"}, {"boundingBox": "1575,651,18,19", "text": "間"}, {"boundingBox": "1574,684,21,4", "text": "一"}, {"boundingBox": "1573,702,21,20", "text": "般"}, {"boundingBox": "1574,729,18,16", "text": "の"}, {"boundingBox": "1572,753,21,18", "text": "人"}, {"boundingBox": "1573,779,17,16", "text": "は"}, {"boundingBox": "1574,804,14,20", "text": "と"}, {"boundingBox": "1573,832,15,18", "text": "も"}, {"boundingBox": "1571,855,18,18", "text": "す"}, {"boundingBox": "1572,882,16,16", "text": "る"}, {"boundingBox": "1571,907,14,19", "text": "と"}, {"boundingBox": "1568,932,21,20", "text": "面"}, {"boundingBox": "1568,958,22,20", "text": "積"}, {"boundingBox": "1569,986,19,16", "text": "の"}, {"boundingBox": "1568,1010,20,20", "text": "廣"}, {"boundingBox": "1567,1035,20,20", "text": "狹"}, {"boundingBox": "1567,1062,18,19", "text": "や"}, {"boundingBox": "1566,1087,20,17", "text": "工"}, {"boundingBox": "1565,1113,20,20", "text": "費"}, {"boundingBox": "1566,1139,18,16", "text": "の"}, {"boundingBox": "1565,1164,19,19", "text": "多"}, {"boundingBox": "1564,1190,20,20", "text": "な"}]}, {"boundingBox": "341,437,19,152", "words": [{"boundingBox": "341,437,18,15", "text": "健"}, {"boundingBox": "343,460,17,15", "text": "築"}, {"boundingBox": "343,484,17,14", "text": "趣"}, {"boundingBox": "343,506,16,14", "text": "味"}, {"boundingBox": "345,532,14,10", "text": "の"}, {"boundingBox": "344,577,16,12", "text": "及"}]}, {"boundingBox": "1708,448,18,105", "words": [{"boundingBox": "1709,448,17,13", "text": "理"}, {"boundingBox": "1709,469,16,17", "text": "想"}, {"boundingBox": "1710,495,14,10", "text": "の"}, {"boundingBox": "1709,515,16,15", "text": "住"}, {"boundingBox": "1708,538,16,15", "text": "宅"}]}, {"boundingBox": "1631,469,36,261", "words": [{"boundingBox": "1634,469,33,31", "text": "建"}, {"boundingBox": "1635,507,31,30", "text": "築"}, {"boundingBox": "1635,547,30,28", "text": "趣"}, {"boundingBox": "1634,584,32,30", "text": "味"}, {"boundingBox": "1635,626,26,21", "text": "の"}, {"boundingBox": "1632,661,31,31", "text": "普"}, {"boundingBox": "1631,701,31,29", "text": "及"}]}, {"boundingBox": "1277,513,24,123", "words": [{"boundingBox": "1279,513,22,20", "text": "住"}, {"boundingBox": "1278,539,22,20", "text": "宅"}, {"boundingBox": "1280,565,17,19", "text": "と"}, {"boundingBox": "1278,590,22,21", "text": "婦"}, {"boundingBox": "1277,617,21,19", "text": "人"}]}, {"boundingBox": "1697,1073,17,28", "words": [{"boundingBox": "1697,1073,17,12", "text": "ニ"}, {"boundingBox": "1697,1088,17,13", "text": "六"}]}, {"boundingBox": "1224,1112,22,97", "words": [{"boundingBox": "1227,1112,17,8", "text": "マ"}, {"boundingBox": "1227,1132,19,16", "text": "ガ"}, {"boundingBox": "1229,1160,15,14", "text": "ジ"}, {"boundingBox": "1227,1188,17,11", "text": "ン"}, {"boundingBox": "1224,1204,11,5", "text": "」"}]}]}]}